mikado/__init__.py
mikado/releasemgmt/__init__.py
mikado_releasemgmt-0.0.3.data/scripts/aws_tools.py
mikado_releasemgmt-0.0.3.data/scripts/hubwrapper.py
mikado_releasemgmt-0.0.3.data/scripts/releaseinator.py
mikado_releasemgmt-0.0.3.dist-info/DESCRIPTION.rst
mikado_releasemgmt-0.0.3.dist-info/METADATA
mikado_releasemgmt-0.0.3.dist-info/RECORD
mikado_releasemgmt-0.0.3.dist-info/WHEEL
mikado_releasemgmt-0.0.3.dist-info/metadata.json
mikado_releasemgmt-0.0.3.dist-info/top_level.txt
