Metadata-Version: 2.0
Name: mikado-releasemgmt
Version: 0.0.3
Summary: A Description to change
Home-page: UNKNOWN
Author: author
Author-email: UNKNOWN
License: UNKNOWN
Platform: UNKNOWN
